evo/data_converters/omf/__init__.py
evo/data_converters/omf/omf_metadata.py
evo/data_converters/omf/omf_reader_context.py
evo/data_converters/omf/utils.py
evo/data_converters/omf/exporter/__init__.py
evo/data_converters/omf/exporter/blocksync_to_omf.py
evo/data_converters/omf/exporter/evo_attributes_to_omf.py
evo/data_converters/omf/exporter/evo_lineset_to_omf.py
evo/data_converters/omf/exporter/evo_pointset_to_omf.py
evo/data_converters/omf/exporter/evo_surface_to_omf.py
evo/data_converters/omf/exporter/evo_to_omf.py
evo/data_converters/omf/exporter/utils.py
evo/data_converters/omf/importer/__init__.py
evo/data_converters/omf/importer/omf_attributes_to_evo.py
evo/data_converters/omf/importer/omf_blockmodel_to_evo.py
evo/data_converters/omf/importer/omf_lineset_to_evo.py
evo/data_converters/omf/importer/omf_pointset_to_evo.py
evo/data_converters/omf/importer/omf_surface_to_evo.py
evo/data_converters/omf/importer/omf_to_evo.py
evo/data_converters/omf/importer/blockmodel/__init__.py
evo/data_converters/omf/importer/blockmodel/omf_attributes_to_blocksync.py
evo/data_converters/omf/importer/blockmodel/omf_blockmodel_to_blocksync.py
evo/data_converters/omf/importer/blockmodel/utils.py
evo_data_converters_omf-0.1.6.dist-info/METADATA
evo_data_converters_omf-0.1.6.dist-info/WHEEL
evo_data_converters_omf-0.1.6.dist-info/licenses/LICENSE.md
evo_data_converters_omf-0.1.6.dist-info/RECORD
