Metadata-Version: 2.4
Name: evo-data-converters-omf
Version: 0.1.6
Summary: Python data converters for OMF to Evo geoscience objects
Project-URL: Source, https://github.com/SeequentEvo/evo-python-sdk
Project-URL: Tracker, https://github.com/SeequentEvo/evo-python-sdk/issues
Project-URL: Homepage, https://www.seequent.com/
Project-URL: Documentation, https://developer.seequent.com/
Author-email: Seequent <support@seequent.com>
License-File: LICENSE.md
Requires-Python: >=3.10
Requires-Dist: evo-data-converters-common>=0.3.1
Requires-Dist: omf2
Requires-Dist: omf>=1.0.1
Requires-Dist: pandas
